capsphere/__init__.py
capsphere/common/__init__.py
capsphere/common/date.py
capsphere/common/env_reader.py
capsphere/common/excel.py
capsphere/common/utils.py
capsphere/common/aws/__init__.py
capsphere/common/aws/s3.py
capsphere/common/aws/sns.py
capsphere/common/aws/textract.py
capsphere/common/aws/test/__init__.py
capsphere/common/aws/test/data.py
capsphere/common/aws/test/test_s3.py
capsphere/common/aws/test/test_textract.py
capsphere/common/domain/__init__.py
capsphere/common/domain/bank.py
capsphere/common/test/__init__.py
capsphere/common/test/test_date.py
capsphere/common/test/test_excel.py
capsphere/common/test/test_utils.py
capsphere/db/__init__.py
capsphere/ocr/__init__.py
capsphere/ocr/annual_report/__init__.py
capsphere/ocr/bank_statement/__init__.py
capsphere/ocr/bank_statement/domain.py
capsphere/ocr/bank_statement/test_domain.py
capsphere/ocr/bank_statement/utils.py
capsphere/ocr/bank_statement/pdfplumber/__init__.py
capsphere/ocr/bank_statement/pdfplumber/converter.py
capsphere/ocr/bank_statement/pdfplumber/reader.py
capsphere/ocr/bank_statement/pdfplumber/test/__init__.py
capsphere/ocr/bank_statement/pdfplumber/test/test_converter.py
capsphere/ocr/bank_statement/pdfplumber/test/test_reader.py
capsphere/ocr/bank_statement/pytesseract/__init__.py
capsphere/ocr/bank_statement/textract/__init__.py
capsphere/ocr/bank_statement/textract/analysis_converter.py
capsphere/ocr/bank_statement/textract/converter.py
capsphere/ocr/bank_statement/textract/extract.py
capsphere/ocr/bank_statement/textract/test/__init__.py
capsphere/ocr/bank_statement/textract/test/test_bank_converter.py
capsphere/ocr/bank_statement/textract/test/test_extract.py
capsphere/resources/__init__.py
capsphere/resources/schema.json
capsphere/resources/test/__init__.py
capsphere/resources/test/ambank.pdf
capsphere/resources/test/data.py
capsphere-0.0.20.dist-info/METADATA
capsphere-0.0.20.dist-info/WHEEL
capsphere-0.0.20.dist-info/top_level.txt
capsphere-0.0.20.dist-info/RECORD
