Metadata-Version: 2.1
Name: capsphere
Version: 0.0.20
Summary: Capsphere proprietary library
Author: Andy Lee
Author-email: andy.mt.lee@gmail.com
Keywords: python,capsphere,pdf,credit,cs
Classifier: Programming Language :: Python :: 3
Classifier: License :: OSI Approved :: MIT License
Classifier: Operating System :: OS Independent
Requires-Dist: boto3
Requires-Dist: dataclass-wizard
Requires-Dist: pandas
Requires-Dist: pdfplumber
Requires-Dist: python-dotenv
Requires-Dist: twine
Requires-Dist: wheel
Requires-Dist: xlsxwriter
